<?xml version="1.0" encoding="utf-8"?>
<!DOCTYPE rrd SYSTEM "https://oss.oetiker.ch/rrdtool/rrdtool.dtd">
<!-- Round Robin Database Dump -->
<rrd>
	<version>0003</version>
	<step>60</step> <!-- Seconds -->
	<lastupdate>1632015427</lastupdate> <!-- 2021-09-18 20:37:07 CDT -->

	<ds>
		<name> inmulti </name>
		<type> COUNTER </type>
		<minimal_heartbeat>600</minimal_heartbeat>
		<min>NaN</min>
		<max>NaN</max>

		<!-- PDP Status -->
		<last_ds>149</last_ds>
		<value>0.0000000000e+00</value>
		<unknown_sec> 0 </unknown_sec>
	</ds>

	<ds>
		<name> ippackets </name>
		<type> COUNTER </type>
		<minimal_heartbeat>600</minimal_heartbeat>
		<min>NaN</min>
		<max>NaN</max>

		<!-- PDP Status -->
		<last_ds>12959</last_ds>
		<value>1.1075282562e+02</value>
		<unknown_sec> 0 </unknown_sec>
	</ds>

	<ds>
		<name> icmpme </name>
		<type> COUNTER </type>
		<minimal_heartbeat>600</minimal_heartbeat>
		<min>NaN</min>
		<max>NaN</max>

		<!-- PDP Status -->
		<last_ds>2</last_ds>
		<value>0.0000000000e+00</value>
		<unknown_sec> 0 </unknown_sec>
	</ds>

	<ds>
		<name> segout </name>
		<type> COUNTER </type>
		<minimal_heartbeat>600</minimal_heartbeat>
		<min>NaN</min>
		<max>NaN</max>

		<!-- PDP Status -->
		<last_ds>133</last_ds>
		<value>0.0000000000e+00</value>
		<unknown_sec> 0 </unknown_sec>
	</ds>

	<ds>
		<name> datagramsin </name>
		<type> COUNTER </type>
		<minimal_heartbeat>600</minimal_heartbeat>
		<min>NaN</min>
		<max>NaN</max>

		<!-- PDP Status -->
		<last_ds>0</last_ds>
		<value>0.0000000000e+00</value>
		<unknown_sec> 0 </unknown_sec>
	</ds>

	<!-- Round Robin Archives -->
	<rra>
		<cf>AVERAGE</cf>
		<pdp_per_row>1</pdp_per_row> <!-- 60 seconds -->

		<params>
		<xff>5.0000000000e-01</xff>
		</params>
		<cdp_prep>
			<ds>
			<primary_value>1.1666666667e-01</primary_value>
			<secondary_value>NaN</secondary_value>
			<value>NaN</value>
			<unknown_datapoints>0</unknown_datapoints>
			</ds>
			<ds>
			<primary_value>8.4782715749e+01</primary_value>
			<secondary_value>NaN</secondary_value>
			<value>NaN</value>
			<unknown_datapoints>0</unknown_datapoints>
			</ds>
			<ds>
			<primary_value>0.0000000000e+00</primary_value>
			<secondary_value>NaN</secondary_value>
			<value>NaN</value>
			<unknown_datapoints>0</unknown_datapoints>
			</ds>
			<ds>
			<primary_value>5.3881137984e-01</primary_value>
			<secondary_value>NaN</secondary_value>
			<value>NaN</value>
			<unknown_datapoints>0</unknown_datapoints>
			</ds>
			<ds>
			<primary_value>0.0000000000e+00</primary_value>
			<secondary_value>NaN</secondary_value>
			<value>NaN</value>
			<unknown_datapoints>0</unknown_datapoints>
			</ds>
		</cdp_prep>
		<database>
			<!-- 2021-09-18 20:18:00 CDT / 1632014280 --> <row><v>NaN</v><v>NaN</v><v>NaN</v><v>NaN</v><v>NaN</v></row>
			<!-- 2021-09-18 20:19:00 CDT / 1632014340 --> <row><v>NaN</v><v>NaN</v><v>NaN</v><v>NaN</v><v>NaN</v></row>
			<!-- 2021-09-18 20:20:00 CDT / 1632014400 --> <row><v>NaN</v><v>NaN</v><v>NaN</v><v>NaN</v><v>NaN</v></row>
			<!-- 2021-09-18 20:21:00 CDT / 1632014460 --> <row><v>NaN</v><v>NaN</v><v>NaN</v><v>NaN</v><v>NaN</v></row>
			<!-- 2021-09-18 20:22:00 CDT / 1632014520 --> <row><v>NaN</v><v>NaN</v><v>NaN</v><v>NaN</v><v>NaN</v></row>
			<!-- 2021-09-18 20:23:00 CDT / 1632014580 --> <row><v>NaN</v><v>NaN</v><v>NaN</v><v>NaN</v><v>NaN</v></row>
			<!-- 2021-09-18 20:24:00 CDT / 1632014640 --> <row><v>NaN</v><v>NaN</v><v>NaN</v><v>NaN</v><v>NaN</v></row>
			<!-- 2021-09-18 20:25:00 CDT / 1632014700 --> <row><v>NaN</v><v>NaN</v><v>NaN</v><v>NaN</v><v>NaN</v></row>
			<!-- 2021-09-18 20:26:00 CDT / 1632014760 --> <row><v>NaN</v><v>NaN</v><v>NaN</v><v>NaN</v><v>NaN</v></row>
			<!-- 2021-09-18 20:27:00 CDT / 1632014820 --> <row><v>NaN</v><v>NaN</v><v>NaN</v><v>NaN</v><v>NaN</v></row>
			<!-- 2021-09-18 20:28:00 CDT / 1632014880 --> <row><v>NaN</v><v>NaN</v><v>NaN</v><v>NaN</v><v>NaN</v></row>
			<!-- 2021-09-18 20:29:00 CDT / 1632014940 --> <row><v>NaN</v><v>NaN</v><v>NaN</v><v>NaN</v><v>NaN</v></row>
			<!-- 2021-09-18 20:30:00 CDT / 1632015000 --> <row><v>NaN</v><v>NaN</v><v>NaN</v><v>NaN</v><v>NaN</v></row>
			<!-- 2021-09-18 20:31:00 CDT / 1632015060 --> <row><v>NaN</v><v>NaN</v><v>NaN</v><v>NaN</v><v>NaN</v></row>
			<!-- 2021-09-18 20:32:00 CDT / 1632015120 --> <row><v>NaN</v><v>NaN</v><v>NaN</v><v>NaN</v><v>NaN</v></row>
			<!-- 2021-09-18 20:33:00 CDT / 1632015180 --> <row><v>NaN</v><v>NaN</v><v>NaN</v><v>NaN</v><v>NaN</v></row>
			<!-- 2021-09-18 20:34:00 CDT / 1632015240 --> <row><v>NaN</v><v>NaN</v><v>NaN</v><v>NaN</v><v>NaN</v></row>
			<!-- 2021-09-18 20:35:00 CDT / 1632015300 --> <row><v>8.4745762712e-02</v><v>2.0951692260e+01</v><v>0.0000000000e+00</v><v>1.8644067797e-01</v><v>0.0000000000e+00</v></row>
			<!-- 2021-09-18 20:36:00 CDT / 1632015360 --> <row><v>1.3333333333e-01</v><v>9.6118906435e+01</v><v>3.3333333333e-02</v><v>1.3945219535e+00</v><v>0.0000000000e+00</v></row>
			<!-- 2021-09-18 20:37:00 CDT / 1632015420 --> <row><v>1.1666666667e-01</v><v>8.4782715749e+01</v><v>0.0000000000e+00</v><v>5.3881137984e-01</v><v>0.0000000000e+00</v></row>
		</database>
	</rra>
	<rra>
		<cf>AVERAGE</cf>
		<pdp_per_row>1</pdp_per_row> <!-- 60 seconds -->

		<params>
		<xff>5.0000000000e-01</xff>
		</params>
		<cdp_prep>
			<ds>
			<primary_value>1.1666666667e-01</primary_value>
			<secondary_value>NaN</secondary_value>
			<value>NaN</value>
			<unknown_datapoints>0</unknown_datapoints>
			</ds>
			<ds>
			<primary_value>8.4782715749e+01</primary_value>
			<secondary_value>NaN</secondary_value>
			<value>NaN</value>
			<unknown_datapoints>0</unknown_datapoints>
			</ds>
			<ds>
			<primary_value>0.0000000000e+00</primary_value>
			<secondary_value>NaN</secondary_value>
			<value>NaN</value>
			<unknown_datapoints>0</unknown_datapoints>
			</ds>
			<ds>
			<primary_value>5.3881137984e-01</primary_value>
			<secondary_value>NaN</secondary_value>
			<value>NaN</value>
			<unknown_datapoints>0</unknown_datapoints>
			</ds>
			<ds>
			<primary_value>0.0000000000e+00</primary_value>
			<secondary_value>NaN</secondary_value>
			<value>NaN</value>
			<unknown_datapoints>0</unknown_datapoints>
			</ds>
		</cdp_prep>
		<database>
			<!-- 2021-09-18 20:18:00 CDT / 1632014280 --> <row><v>NaN</v><v>NaN</v><v>NaN</v><v>NaN</v><v>NaN</v></row>
			<!-- 2021-09-18 20:19:00 CDT / 1632014340 --> <row><v>NaN</v><v>NaN</v><v>NaN</v><v>NaN</v><v>NaN</v></row>
			<!-- 2021-09-18 20:20:00 CDT / 1632014400 --> <row><v>NaN</v><v>NaN</v><v>NaN</v><v>NaN</v><v>NaN</v></row>
			<!-- 2021-09-18 20:21:00 CDT / 1632014460 --> <row><v>NaN</v><v>NaN</v><v>NaN</v><v>NaN</v><v>NaN</v></row>
			<!-- 2021-09-18 20:22:00 CDT / 1632014520 --> <row><v>NaN</v><v>NaN</v><v>NaN</v><v>NaN</v><v>NaN</v></row>
			<!-- 2021-09-18 20:23:00 CDT / 1632014580 --> <row><v>NaN</v><v>NaN</v><v>NaN</v><v>NaN</v><v>NaN</v></row>
			<!-- 2021-09-18 20:24:00 CDT / 1632014640 --> <row><v>NaN</v><v>NaN</v><v>NaN</v><v>NaN</v><v>NaN</v></row>
			<!-- 2021-09-18 20:25:00 CDT / 1632014700 --> <row><v>NaN</v><v>NaN</v><v>NaN</v><v>NaN</v><v>NaN</v></row>
			<!-- 2021-09-18 20:26:00 CDT / 1632014760 --> <row><v>NaN</v><v>NaN</v><v>NaN</v><v>NaN</v><v>NaN</v></row>
			<!-- 2021-09-18 20:27:00 CDT / 1632014820 --> <row><v>NaN</v><v>NaN</v><v>NaN</v><v>NaN</v><v>NaN</v></row>
			<!-- 2021-09-18 20:28:00 CDT / 1632014880 --> <row><v>NaN</v><v>NaN</v><v>NaN</v><v>NaN</v><v>NaN</v></row>
			<!-- 2021-09-18 20:29:00 CDT / 1632014940 --> <row><v>NaN</v><v>NaN</v><v>NaN</v><v>NaN</v><v>NaN</v></row>
			<!-- 2021-09-18 20:30:00 CDT / 1632015000 --> <row><v>NaN</v><v>NaN</v><v>NaN</v><v>NaN</v><v>NaN</v></row>
			<!-- 2021-09-18 20:31:00 CDT / 1632015060 --> <row><v>NaN</v><v>NaN</v><v>NaN</v><v>NaN</v><v>NaN</v></row>
			<!-- 2021-09-18 20:32:00 CDT / 1632015120 --> <row><v>NaN</v><v>NaN</v><v>NaN</v><v>NaN</v><v>NaN</v></row>
			<!-- 2021-09-18 20:33:00 CDT / 1632015180 --> <row><v>NaN</v><v>NaN</v><v>NaN</v><v>NaN</v><v>NaN</v></row>
			<!-- 2021-09-18 20:34:00 CDT / 1632015240 --> <row><v>NaN</v><v>NaN</v><v>NaN</v><v>NaN</v><v>NaN</v></row>
			<!-- 2021-09-18 20:35:00 CDT / 1632015300 --> <row><v>8.4745762712e-02</v><v>2.0951692260e+01</v><v>0.0000000000e+00</v><v>1.8644067797e-01</v><v>0.0000000000e+00</v></row>
			<!-- 2021-09-18 20:36:00 CDT / 1632015360 --> <row><v>1.3333333333e-01</v><v>9.6118906435e+01</v><v>3.3333333333e-02</v><v>1.3945219535e+00</v><v>0.0000000000e+00</v></row>
			<!-- 2021-09-18 20:37:00 CDT / 1632015420 --> <row><v>1.1666666667e-01</v><v>8.4782715749e+01</v><v>0.0000000000e+00</v><v>5.3881137984e-01</v><v>0.0000000000e+00</v></row>
		</database>
	</rra>
	<rra>
		<cf>AVERAGE</cf>
		<pdp_per_row>1</pdp_per_row> <!-- 60 seconds -->

		<params>
		<xff>5.0000000000e-01</xff>
		</params>
		<cdp_prep>
			<ds>
			<primary_value>1.1666666667e-01</primary_value>
			<secondary_value>NaN</secondary_value>
			<value>NaN</value>
			<unknown_datapoints>0</unknown_datapoints>
			</ds>
			<ds>
			<primary_value>8.4782715749e+01</primary_value>
			<secondary_value>NaN</secondary_value>
			<value>NaN</value>
			<unknown_datapoints>0</unknown_datapoints>
			</ds>
			<ds>
			<primary_value>0.0000000000e+00</primary_value>
			<secondary_value>NaN</secondary_value>
			<value>NaN</value>
			<unknown_datapoints>0</unknown_datapoints>
			</ds>
			<ds>
			<primary_value>5.3881137984e-01</primary_value>
			<secondary_value>NaN</secondary_value>
			<value>NaN</value>
			<unknown_datapoints>0</unknown_datapoints>
			</ds>
			<ds>
			<primary_value>0.0000000000e+00</primary_value>
			<secondary_value>NaN</secondary_value>
			<value>NaN</value>
			<unknown_datapoints>0</unknown_datapoints>
			</ds>
		</cdp_prep>
		<database>
			<!-- 2021-09-18 20:18:00 CDT / 1632014280 --> <row><v>NaN</v><v>NaN</v><v>NaN</v><v>NaN</v><v>NaN</v></row>
			<!-- 2021-09-18 20:19:00 CDT / 1632014340 --> <row><v>NaN</v><v>NaN</v><v>NaN</v><v>NaN</v><v>NaN</v></row>
			<!-- 2021-09-18 20:20:00 CDT / 1632014400 --> <row><v>NaN</v><v>NaN</v><v>NaN</v><v>NaN</v><v>NaN</v></row>
			<!-- 2021-09-18 20:21:00 CDT / 1632014460 --> <row><v>NaN</v><v>NaN</v><v>NaN</v><v>NaN</v><v>NaN</v></row>
			<!-- 2021-09-18 20:22:00 CDT / 1632014520 --> <row><v>NaN</v><v>NaN</v><v>NaN</v><v>NaN</v><v>NaN</v></row>
			<!-- 2021-09-18 20:23:00 CDT / 1632014580 --> <row><v>NaN</v><v>NaN</v><v>NaN</v><v>NaN</v><v>NaN</v></row>
			<!-- 2021-09-18 20:24:00 CDT / 1632014640 --> <row><v>NaN</v><v>NaN</v><v>NaN</v><v>NaN</v><v>NaN</v></row>
			<!-- 2021-09-18 20:25:00 CDT / 1632014700 --> <row><v>NaN</v><v>NaN</v><v>NaN</v><v>NaN</v><v>NaN</v></row>
			<!-- 2021-09-18 20:26:00 CDT / 1632014760 --> <row><v>NaN</v><v>NaN</v><v>NaN</v><v>NaN</v><v>NaN</v></row>
			<!-- 2021-09-18 20:27:00 CDT / 1632014820 --> <row><v>NaN</v><v>NaN</v><v>NaN</v><v>NaN</v><v>NaN</v></row>
			<!-- 2021-09-18 20:28:00 CDT / 1632014880 --> <row><v>NaN</v><v>NaN</v><v>NaN</v><v>NaN</v><v>NaN</v></row>
			<!-- 2021-09-18 20:29:00 CDT / 1632014940 --> <row><v>NaN</v><v>NaN</v><v>NaN</v><v>NaN</v><v>NaN</v></row>
			<!-- 2021-09-18 20:30:00 CDT / 1632015000 --> <row><v>NaN</v><v>NaN</v><v>NaN</v><v>NaN</v><v>NaN</v></row>
			<!-- 2021-09-18 20:31:00 CDT / 1632015060 --> <row><v>NaN</v><v>NaN</v><v>NaN</v><v>NaN</v><v>NaN</v></row>
			<!-- 2021-09-18 20:32:00 CDT / 1632015120 --> <row><v>NaN</v><v>NaN</v><v>NaN</v><v>NaN</v><v>NaN</v></row>
			<!-- 2021-09-18 20:33:00 CDT / 1632015180 --> <row><v>NaN</v><v>NaN</v><v>NaN</v><v>NaN</v><v>NaN</v></row>
			<!-- 2021-09-18 20:34:00 CDT / 1632015240 --> <row><v>NaN</v><v>NaN</v><v>NaN</v><v>NaN</v><v>NaN</v></row>
			<!-- 2021-09-18 20:35:00 CDT / 1632015300 --> <row><v>8.4745762712e-02</v><v>2.0951692260e+01</v><v>0.0000000000e+00</v><v>1.8644067797e-01</v><v>0.0000000000e+00</v></row>
			<!-- 2021-09-18 20:36:00 CDT / 1632015360 --> <row><v>1.3333333333e-01</v><v>9.6118906435e+01</v><v>3.3333333333e-02</v><v>1.3945219535e+00</v><v>0.0000000000e+00</v></row>
			<!-- 2021-09-18 20:37:00 CDT / 1632015420 --> <row><v>1.1666666667e-01</v><v>8.4782715749e+01</v><v>0.0000000000e+00</v><v>5.3881137984e-01</v><v>0.0000000000e+00</v></row>
		</database>
	</rra>
	<rra>
		<cf>AVERAGE</cf>
		<pdp_per_row>1</pdp_per_row> <!-- 60 seconds -->

		<params>
		<xff>5.0000000000e-01</xff>
		</params>
		<cdp_prep>
			<ds>
			<primary_value>1.1666666667e-01</primary_value>
			<secondary_value>NaN</secondary_value>
			<value>NaN</value>
			<unknown_datapoints>0</unknown_datapoints>
			</ds>
			<ds>
			<primary_value>8.4782715749e+01</primary_value>
			<secondary_value>NaN</secondary_value>
			<value>NaN</value>
			<unknown_datapoints>0</unknown_datapoints>
			</ds>
			<ds>
			<primary_value>0.0000000000e+00</primary_value>
			<secondary_value>NaN</secondary_value>
			<value>NaN</value>
			<unknown_datapoints>0</unknown_datapoints>
			</ds>
			<ds>
			<primary_value>5.3881137984e-01</primary_value>
			<secondary_value>NaN</secondary_value>
			<value>NaN</value>
			<unknown_datapoints>0</unknown_datapoints>
			</ds>
			<ds>
			<primary_value>0.0000000000e+00</primary_value>
			<secondary_value>NaN</secondary_value>
			<value>NaN</value>
			<unknown_datapoints>0</unknown_datapoints>
			</ds>
		</cdp_prep>
		<database>
			<!-- 2021-09-18 20:18:00 CDT / 1632014280 --> <row><v>NaN</v><v>NaN</v><v>NaN</v><v>NaN</v><v>NaN</v></row>
			<!-- 2021-09-18 20:19:00 CDT / 1632014340 --> <row><v>NaN</v><v>NaN</v><v>NaN</v><v>NaN</v><v>NaN</v></row>
			<!-- 2021-09-18 20:20:00 CDT / 1632014400 --> <row><v>NaN</v><v>NaN</v><v>NaN</v><v>NaN</v><v>NaN</v></row>
			<!-- 2021-09-18 20:21:00 CDT / 1632014460 --> <row><v>NaN</v><v>NaN</v><v>NaN</v><v>NaN</v><v>NaN</v></row>
			<!-- 2021-09-18 20:22:00 CDT / 1632014520 --> <row><v>NaN</v><v>NaN</v><v>NaN</v><v>NaN</v><v>NaN</v></row>
			<!-- 2021-09-18 20:23:00 CDT / 1632014580 --> <row><v>NaN</v><v>NaN</v><v>NaN</v><v>NaN</v><v>NaN</v></row>
			<!-- 2021-09-18 20:24:00 CDT / 1632014640 --> <row><v>NaN</v><v>NaN</v><v>NaN</v><v>NaN</v><v>NaN</v></row>
			<!-- 2021-09-18 20:25:00 CDT / 1632014700 --> <row><v>NaN</v><v>NaN</v><v>NaN</v><v>NaN</v><v>NaN</v></row>
			<!-- 2021-09-18 20:26:00 CDT / 1632014760 --> <row><v>NaN</v><v>NaN</v><v>NaN</v><v>NaN</v><v>NaN</v></row>
			<!-- 2021-09-18 20:27:00 CDT / 1632014820 --> <row><v>NaN</v><v>NaN</v><v>NaN</v><v>NaN</v><v>NaN</v></row>
			<!-- 2021-09-18 20:28:00 CDT / 1632014880 --> <row><v>NaN</v><v>NaN</v><v>NaN</v><v>NaN</v><v>NaN</v></row>
			<!-- 2021-09-18 20:29:00 CDT / 1632014940 --> <row><v>NaN</v><v>NaN</v><v>NaN</v><v>NaN</v><v>NaN</v></row>
			<!-- 2021-09-18 20:30:00 CDT / 1632015000 --> <row><v>NaN</v><v>NaN</v><v>NaN</v><v>NaN</v><v>NaN</v></row>
			<!-- 2021-09-18 20:31:00 CDT / 1632015060 --> <row><v>NaN</v><v>NaN</v><v>NaN</v><v>NaN</v><v>NaN</v></row>
			<!-- 2021-09-18 20:32:00 CDT / 1632015120 --> <row><v>NaN</v><v>NaN</v><v>NaN</v><v>NaN</v><v>NaN</v></row>
			<!-- 2021-09-18 20:33:00 CDT / 1632015180 --> <row><v>NaN</v><v>NaN</v><v>NaN</v><v>NaN</v><v>NaN</v></row>
			<!-- 2021-09-18 20:34:00 CDT / 1632015240 --> <row><v>NaN</v><v>NaN</v><v>NaN</v><v>NaN</v><v>NaN</v></row>
			<!-- 2021-09-18 20:35:00 CDT / 1632015300 --> <row><v>8.4745762712e-02</v><v>2.0951692260e+01</v><v>0.0000000000e+00</v><v>1.8644067797e-01</v><v>0.0000000000e+00</v></row>
			<!-- 2021-09-18 20:36:00 CDT / 1632015360 --> <row><v>1.3333333333e-01</v><v>9.6118906435e+01</v><v>3.3333333333e-02</v><v>1.3945219535e+00</v><v>0.0000000000e+00</v></row>
			<!-- 2021-09-18 20:37:00 CDT / 1632015420 --> <row><v>1.1666666667e-01</v><v>8.4782715749e+01</v><v>0.0000000000e+00</v><v>5.3881137984e-01</v><v>0.0000000000e+00</v></row>
		</database>
	</rra>
	<rra>
		<cf>AVERAGE</cf>
		<pdp_per_row>1</pdp_per_row> <!-- 60 seconds -->

		<params>
		<xff>5.0000000000e-01</xff>
		</params>
		<cdp_prep>
			<ds>
			<primary_value>1.1666666667e-01</primary_value>
			<secondary_value>NaN</secondary_value>
			<value>NaN</value>
			<unknown_datapoints>0</unknown_datapoints>
			</ds>
			<ds>
			<primary_value>8.4782715749e+01</primary_value>
			<secondary_value>NaN</secondary_value>
			<value>NaN</value>
			<unknown_datapoints>0</unknown_datapoints>
			</ds>
			<ds>
			<primary_value>0.0000000000e+00</primary_value>
			<secondary_value>NaN</secondary_value>
			<value>NaN</value>
			<unknown_datapoints>0</unknown_datapoints>
			</ds>
			<ds>
			<primary_value>5.3881137984e-01</primary_value>
			<secondary_value>NaN</secondary_value>
			<value>NaN</value>
			<unknown_datapoints>0</unknown_datapoints>
			</ds>
			<ds>
			<primary_value>0.0000000000e+00</primary_value>
			<secondary_value>NaN</secondary_value>
			<value>NaN</value>
			<unknown_datapoints>0</unknown_datapoints>
			</ds>
		</cdp_prep>
		<database>
			<!-- 2021-09-18 20:18:00 CDT / 1632014280 --> <row><v>NaN</v><v>NaN</v><v>NaN</v><v>NaN</v><v>NaN</v></row>
			<!-- 2021-09-18 20:19:00 CDT / 1632014340 --> <row><v>NaN</v><v>NaN</v><v>NaN</v><v>NaN</v><v>NaN</v></row>
			<!-- 2021-09-18 20:20:00 CDT / 1632014400 --> <row><v>NaN</v><v>NaN</v><v>NaN</v><v>NaN</v><v>NaN</v></row>
			<!-- 2021-09-18 20:21:00 CDT / 1632014460 --> <row><v>NaN</v><v>NaN</v><v>NaN</v><v>NaN</v><v>NaN</v></row>
			<!-- 2021-09-18 20:22:00 CDT / 1632014520 --> <row><v>NaN</v><v>NaN</v><v>NaN</v><v>NaN</v><v>NaN</v></row>
			<!-- 2021-09-18 20:23:00 CDT / 1632014580 --> <row><v>NaN</v><v>NaN</v><v>NaN</v><v>NaN</v><v>NaN</v></row>
			<!-- 2021-09-18 20:24:00 CDT / 1632014640 --> <row><v>NaN</v><v>NaN</v><v>NaN</v><v>NaN</v><v>NaN</v></row>
			<!-- 2021-09-18 20:25:00 CDT / 1632014700 --> <row><v>NaN</v><v>NaN</v><v>NaN</v><v>NaN</v><v>NaN</v></row>
			<!-- 2021-09-18 20:26:00 CDT / 1632014760 --> <row><v>NaN</v><v>NaN</v><v>NaN</v><v>NaN</v><v>NaN</v></row>
			<!-- 2021-09-18 20:27:00 CDT / 1632014820 --> <row><v>NaN</v><v>NaN</v><v>NaN</v><v>NaN</v><v>NaN</v></row>
			<!-- 2021-09-18 20:28:00 CDT / 1632014880 --> <row><v>NaN</v><v>NaN</v><v>NaN</v><v>NaN</v><v>NaN</v></row>
			<!-- 2021-09-18 20:29:00 CDT / 1632014940 --> <row><v>NaN</v><v>NaN</v><v>NaN</v><v>NaN</v><v>NaN</v></row>
			<!-- 2021-09-18 20:30:00 CDT / 1632015000 --> <row><v>NaN</v><v>NaN</v><v>NaN</v><v>NaN</v><v>NaN</v></row>
			<!-- 2021-09-18 20:31:00 CDT / 1632015060 --> <row><v>NaN</v><v>NaN</v><v>NaN</v><v>NaN</v><v>NaN</v></row>
			<!-- 2021-09-18 20:32:00 CDT / 1632015120 --> <row><v>NaN</v><v>NaN</v><v>NaN</v><v>NaN</v><v>NaN</v></row>
			<!-- 2021-09-18 20:33:00 CDT / 1632015180 --> <row><v>NaN</v><v>NaN</v><v>NaN</v><v>NaN</v><v>NaN</v></row>
			<!-- 2021-09-18 20:34:00 CDT / 1632015240 --> <row><v>NaN</v><v>NaN</v><v>NaN</v><v>NaN</v><v>NaN</v></row>
			<!-- 2021-09-18 20:35:00 CDT / 1632015300 --> <row><v>8.4745762712e-02</v><v>2.0951692260e+01</v><v>0.0000000000e+00</v><v>1.8644067797e-01</v><v>0.0000000000e+00</v></row>
			<!-- 2021-09-18 20:36:00 CDT / 1632015360 --> <row><v>1.3333333333e-01</v><v>9.6118906435e+01</v><v>3.3333333333e-02</v><v>1.3945219535e+00</v><v>0.0000000000e+00</v></row>
			<!-- 2021-09-18 20:37:00 CDT / 1632015420 --> <row><v>1.1666666667e-01</v><v>8.4782715749e+01</v><v>0.0000000000e+00</v><v>5.3881137984e-01</v><v>0.0000000000e+00</v></row>
		</database>
	</rra>
</rrd>
